{"name":"build-javascript","namedChunkGroups":{"polyfill":{"name":"polyfill","assets":[{"name":"webpack-runtime-1bbf5863d6d4f2e9a54e.js","size":4522},{"name":"polyfill-28dbfa58150ea9910781.js","size":85836}],"filteredAssets":0,"assetsSize":90358,"filteredAuxiliaryAssets":2,"auxiliaryAssetsSize":225754},"app":{"name":"app","assets":[{"name":"webpack-runtime-1bbf5863d6d4f2e9a54e.js","size":4522},{"name":"styles.4da6df3329578b809d56.css","size":3688},{"name":"framework-deb5402af5b406c6372a.js","size":129749},{"name":"app-6169ae8d02de545c4303.js","size":55911}],"filteredAssets":0,"assetsSize":193870,"filteredAuxiliaryAssets":3,"auxiliaryAssetsSize":564767},"component---src-pages-404-tsx":{"name":"component---src-pages-404-tsx","assets":[{"name":"styles.4da6df3329578b809d56.css","size":3688},{"name":"a3336d3c033a5ec9d59a088cb032c68b95c64a61-ca47c45746901dd133fc.js","size":17495},{"name":"component---src-pages-404-tsx-e43e7a1b0ea5a425ce9c.js","size":495}],"filteredAssets":0,"assetsSize":21678,"filteredAuxiliaryAssets":2,"auxiliaryAssetsSize":69890},"component---src-pages-about-tsx":{"name":"component---src-pages-about-tsx","assets":[{"name":"styles.4da6df3329578b809d56.css","size":3688},{"name":"component---src-pages-about-tsx-bcf33a216acddcdaa7c3.js","size":2744}],"filteredAssets":0,"assetsSize":6432,"filteredAuxiliaryAssets":1,"auxiliaryAssetsSize":5557},"component---src-pages-contact-tsx":{"name":"component---src-pages-contact-tsx","assets":[{"name":"styles.4da6df3329578b809d56.css","size":3688},{"name":"component---src-pages-contact-tsx-e8d81e85b30aeb41a6b2.js","size":2800}],"filteredAssets":0,"assetsSize":6488,"filteredAuxiliaryAssets":1,"auxiliaryAssetsSize":5710},"component---src-pages-index-tsx":{"name":"component---src-pages-index-tsx","assets":[{"name":"styles.4da6df3329578b809d56.css","size":3688},{"name":"a3336d3c033a5ec9d59a088cb032c68b95c64a61-ca47c45746901dd133fc.js","size":17495},{"name":"component---src-pages-index-tsx-b4a637919fae15368cbf.js","size":4700}],"filteredAssets":0,"assetsSize":25883,"filteredAuxiliaryAssets":2,"auxiliaryAssetsSize":79206}},"assetsByChunkName":{"polyfill":["webpack-runtime-1bbf5863d6d4f2e9a54e.js","polyfill-28dbfa58150ea9910781.js"],"app":["webpack-runtime-1bbf5863d6d4f2e9a54e.js","styles.4da6df3329578b809d56.css","framework-deb5402af5b406c6372a.js","app-6169ae8d02de545c4303.js"],"component---src-pages-404-tsx":["styles.4da6df3329578b809d56.css","a3336d3c033a5ec9d59a088cb032c68b95c64a61-ca47c45746901dd133fc.js","component---src-pages-404-tsx-e43e7a1b0ea5a425ce9c.js"],"component---src-pages-about-tsx":["styles.4da6df3329578b809d56.css","component---src-pages-about-tsx-bcf33a216acddcdaa7c3.js"],"component---src-pages-contact-tsx":["styles.4da6df3329578b809d56.css","component---src-pages-contact-tsx-e8d81e85b30aeb41a6b2.js"],"component---src-pages-index-tsx":["styles.4da6df3329578b809d56.css","a3336d3c033a5ec9d59a088cb032c68b95c64a61-ca47c45746901dd133fc.js","component---src-pages-index-tsx-b4a637919fae15368cbf.js"]},"childAssetsByChunkName":{}}